aether/__init__.py
aether/sdk/__init__.py
aether/sdk/admin.py
aether/sdk/apps.py
aether/sdk/cache.py
aether/sdk/context_processors.py
aether/sdk/unittest.py
aether/sdk/utils.py
aether/sdk/auth/__init__.py
aether/sdk/auth/authentication.py
aether/sdk/auth/utils.py
aether/sdk/auth/views.py
aether/sdk/auth/apptoken/__init__.py
aether/sdk/auth/apptoken/admin.py
aether/sdk/auth/apptoken/apps.py
aether/sdk/auth/apptoken/decorators.py
aether/sdk/auth/apptoken/models.py
aether/sdk/auth/apptoken/views.py
aether/sdk/auth/apptoken/migrations/0001_initial.py
aether/sdk/auth/apptoken/migrations/0002_unique_together.py
aether/sdk/auth/apptoken/migrations/__init__.py
aether/sdk/auth/keycloak/__init__.py
aether/sdk/auth/keycloak/forms.py
aether/sdk/auth/keycloak/middleware.py
aether/sdk/auth/keycloak/utils.py
aether/sdk/auth/keycloak/views.py
aether/sdk/conf/__init__.py
aether/sdk/conf/log_filter.py
aether/sdk/conf/settings.py
aether/sdk/conf/settings_aether.py
aether/sdk/conf/storages.py
aether/sdk/conf/urls.py
aether/sdk/drf/__init__.py
aether/sdk/drf/fields.py
aether/sdk/drf/pagination.py
aether/sdk/drf/renderers.py
aether/sdk/drf/serializers.py
aether/sdk/drf/views.py
aether/sdk/health/__init__.py
aether/sdk/health/utils.py
aether/sdk/health/views.py
aether/sdk/management/__init__.py
aether/sdk/management/commands/__init__.py
aether/sdk/management/commands/cdn_publish.py
aether/sdk/management/commands/check_url.py
aether/sdk/management/commands/create_user.py
aether/sdk/management/commands/setup_admin.py
aether/sdk/multitenancy/__init__.py
aether/sdk/multitenancy/admin.py
aether/sdk/multitenancy/apps.py
aether/sdk/multitenancy/models.py
aether/sdk/multitenancy/permissions.py
aether/sdk/multitenancy/serializers.py
aether/sdk/multitenancy/utils.py
aether/sdk/multitenancy/views.py
aether/sdk/multitenancy/migrations/0001_initial.py
aether/sdk/multitenancy/migrations/__init__.py
aether/sdk/static/aether/css/styles.css
aether/sdk/static/aether/images/aether-white.png
aether.sdk-1.4.4.dist-info/LICENSE
aether.sdk-1.4.4.dist-info/METADATA
aether.sdk-1.4.4.dist-info/WHEEL
aether.sdk-1.4.4.dist-info/top_level.txt
aether.sdk-1.4.4.dist-info/RECORD
