Metadata-Version: 2.1
Name: aether.sdk
Version: 1.4.4
Summary: A python library with helpful django tools for Aether
Home-page: https://github.com/eHealthAfrica/aether-django-sdk-library/
Author: eHealth Africa
Author-email: info@ehealthafrica.org
License: Apache2 License
Keywords: django,setup,auth,token,keycloak,multitenancy
Classifier: Development Status :: 5 - Production/Stable
Classifier: Environment :: Web Environment
Classifier: Framework :: Django :: 2.2
Classifier: Framework :: Django :: 3.0
Classifier: Framework :: Django :: 3.1
Classifier: Framework :: Django :: 3.2
Classifier: Intended Audience :: Developers
Classifier: License :: OSI Approved :: Apache Software License
Classifier: Natural Language :: English
Classifier: Operating System :: OS Independent
Classifier: Programming Language :: Python :: 3 :: Only
Classifier: Topic :: Software Development :: Libraries :: Python Modules
Requires-Python: >=3.6
License-File: LICENSE
Requires-Dist: django (<4)
Requires-Dist: django-cors-headers
Requires-Dist: django-debug-toolbar
Requires-Dist: django-postgrespool2
Requires-Dist: django-prometheus
Requires-Dist: django-silk
Requires-Dist: django-uwsgi
Requires-Dist: djangorestframework (>=3.8)
Requires-Dist: drf-dynamic-fields
Requires-Dist: markdown
Requires-Dist: psycopg2-binary
Requires-Dist: pygments
Requires-Dist: python-json-logger
Requires-Dist: requests[security]
Requires-Dist: SQLAlchemy (<2)
Requires-Dist: uwsgi
Provides-Extra: cache
Requires-Dist: django-cacheops ; extra == 'cache'
Requires-Dist: django-redis ; extra == 'cache'
Provides-Extra: scheduler
Requires-Dist: django-rq ; extra == 'scheduler'
Requires-Dist: redis ; extra == 'scheduler'
Requires-Dist: rq ; extra == 'scheduler'
Requires-Dist: rq-scheduler ; extra == 'scheduler'
Provides-Extra: server
Requires-Dist: sentry-sdk ; extra == 'server'
Provides-Extra: storage
Requires-Dist: django-cleanup ; extra == 'storage'
Requires-Dist: django-minio-storage ; extra == 'storage'
Requires-Dist: django-storages[boto3,google] ; extra == 'storage'
Provides-Extra: test
Requires-Dist: coverage ; extra == 'test'
Requires-Dist: flake8 (<6) ; extra == 'test'
Requires-Dist: flake8-quotes ; extra == 'test'
Requires-Dist: tblib ; extra == 'test'
Provides-Extra: webpack
Requires-Dist: django-webpack-loader ; extra == 'webpack'
